{
    "type": "AdaptiveCard",
    "$schema": "http://adaptivecards.io/schemas/adaptive-card.json",
    "version": "1.4",
    "body": [
        {
            "type": "Container",
            "items": [
                {
                    "type": "TextBlock",
                    "size": "extraLarge",
                    "weight": "lighter",
                    "text": "${title}",
                    "wrap": true
                }
            ],
            "bleed": true
        },
        {
            "type": "ColumnSet",
            "columns": [
                {
                    "type": "Column",
                    "width": "50px",
                    "verticalContentAlignment": "center",
                    "items": [
                        {
                            "type": "Container",
                            "items": [
                                {
                                    "type": "Image",
                                    "horizontalAlignment": "center",
                                    "url": "${user.avatar_url}",
                                    "altText": "${user.login}"
                                }
                            ]
                        }
                    ]
                },
                {
                    "type": "Column",
                    "items": [
                        {
                            "type": "Container",
                            "items": [
                                {
                                    "type": "TextBlock",
                                    "size": "medium",
                                    "weight": "lighter",
                                    "text": "Submitted by ${user.login}",
                                    "wrap": true
                                },
                                {
                                    "type": "TextBlock",
                                    "size": "medium",
                                    "weight": "lighter",
                                    "text": "Submitted on ${created_at}",
                                    "wrap": true
                                }
                            ],
                            "bleed": true
                        }
                    ]
                }
            ]
        },
        {
            "type": "ColumnSet",
            "columns": [
                {
                    "type": "Column",
                    "items": [
                        {
                            "type": "Container",
                            "spacing": "none",
                            "style": "emphasis",
                            "items": [
                                {
                                    "type": "TextBlock",
                                    "spacing": "small",
                                    "text": "${state}",
                                    "wrap": true
                                },
                                {
                                    "type": "TextBlock",
                                    "spacing": "none",
                                    "text": "${url}",
                                    "wrap": true
                                }
                            ],
                            "bleed": true,
                            "height": "stretch"
                        }
                    ],
                    "width": 45
                },
                {
                    "type": "Column",
                    "items": [
                        {
                            "type": "Container",
                            "height": "stretch",
                            "items": [
                                {
                                    "type": "ColumnSet",
                                    "columns": [
                                        {
                                            "type": "Column",
                                            "verticalContentAlignment": "center",
                                            "items": [
                                                {
                                                    "type": "Image",
                                                    "url": "${user.avatar_url}"
                                                }
                                            ],
                                            "width": "stretch"
                                        }
                                    ]
                                },
                                {
                                    "type": "ActionSet",
                                    "separator": true,
                                    "actions": [
                                        {
                                            "type": "Action.OpenUrl",
                                            "title": "Web site",
                                            "url": "https://adaptivecards.io"
                                        }
                                    ],
                                    "spacing": "medium"
                                }
                            ]
                        }
                    ],
                    "width": 55
                }
            ],
            "height": "stretch"
        }
    ]
}